Workbook

Sheet Presentation
A1: Which Job Would You Rather Have? | M1: Income | N1: Group DI | O1: Group DI After Tax | P1: With IDI | Q1: Tax Brackets
M2: =A9 | N2: =IF(N8*M2/12>N9,N9*12,M2*N8) | O2: =IF($N$10="Yes",N2*(1-S2),N2) | P2: =O2+(INDEX(#REF!,MATCH(1,#REF!,0))*12) | Q2: 0.1 | R2: 18500 | S2: =INDEX(Q2:Q8,MATCH(M2,R2:R8,1))
A3: Job A | F3: Job B | Q3: 0.15 | R3: 75300
Q4: 0.25 | R4: 151900
Q5: 0.28 | R5: 231450
Q6: 0.33 | R6: 413350
A7: Income While Working | F7: Income While Working | Q7: 0.35 | R7: 466950
M8: Group % | N8: =#REF! | Q8: 0.396 | R8: 20000000
A9: =#REF!+#REF! | F9: =#REF!+#REF!-(INDEX(#REF!,MATCH(1,#REF!,0))*12) | M9: Cap | N9: =#REF!
M10: Taxable | N10: =#REF!
A12: Income While Disabled | F12: Income While Disabled | M12: What's YOUR Income Gap?
M13: Salary | N13: 180000
A14: =#REF!*12 | F14: =#REF!*12+(INDEX(#REF!,MATCH(1,#REF!,0))*12) | M14: Bonus | N14: 20000
M15: Gross Income | N15: =N13+N14
M16: Tax Bracket | N16: 0.28
M17: Net Income | N17: =N15*(1-N16)
M18: Group DI | N18: =IF(N10="Yes",0.75*IF(N13*N8/12>N9,N9,N13*N8),IF(N13*N8/12>N9,N9,N13*N8))
M19: Income GAP | N19: =N17-N18
B36: Why Use Insurance?
B39: Monthly Premium | H39: 450
B40: Monthly Benefit | H40: 10000
B41: Rate of Return | H41: 0.06
B42: Months without an Income | H42: 12
B44: Benefits Received | H44: ='Prem v Self'!T7
B46: What Month would you breakeven? | H46: =NPER(H41/12,H39,0,-H44)
B48: Number of years you need to self insure | H48: =H46/12

Sheet Prem v Self
A2: Month | B2: Mo/$ | C2: Mo/Ret | D2: Investment | E2: Month | F2: Mo/$ | G2: Mo/Ret | H2: Investment | I2: Month | J2: Mo/$ | K2: Mo/Ret | L2: Investment | M2: Month | N2: Mo/$ | O2: Mo/Ret | P2: Investment | Q2: Mo | R2: Benefit | T2: =Presentation!H39 | U2: Monthly Premium
A3: 1 | B3: =$T$2 | C3: =1+($T$4/12) | D3: =B3*C3 | E3: 42 | F3: =$T$2 | G3: =1+($T$4/12) | H3: =(D43+F3)*G3 | I3: 83 | J3: =$T$2 | K3: =1+($T$4/12) | L3: =(H43+J3)*K3 | M3: 124 | N3: =$T$2 | O3: =1+($T$4/12) | P3: =(L43+N3)*O3 | Q3: 1 | R3: =T3 | T3: =Presentation!H40 | U3: Monthly Benefit
A4: 2 | B4: =$T$2 | C4: =1+($T$4/12) | D4: =(D3+B4)*C4 | E4: 43 | F4: =$T$2 | G4: =1+($T$4/12) | H4: =(H3+F4)*G4 | I4: 84 | J4: =$T$2 | K4: =1+($T$4/12) | L4: =(L3+J4)*K4 | M4: 125 | N4: =$T$2 | O4: =1+($T$4/12) | P4: =(P3+N4)*O4 | Q4: 2 | R4: =R3+$T$3 | T4: =Presentation!H41 | U4: Rate of Return
A5: 3 | B5: =$T$2 | C5: =1+($T$4/12) | D5: =(D4+B5)*C5 | E5: 44 | F5: =$T$2 | G5: =1+($T$4/12) | H5: =(H4+F5)*G5 | I5: 85 | J5: =$T$2 | K5: =1+($T$4/12) | L5: =(L4+J5)*K5 | M5: 126 | N5: =$T$2 | O5: =1+($T$4/12) | P5: =(P4+N5)*O5 | Q5: 3 | R5: =R4+$T$3 | T5: =Presentation!H42 | U5: Months without an Income
A6: 4 | B6: =$T$2 | C6: =1+($T$4/12) | D6: =(D5+B6)*C6 | E6: 45 | F6: =$T$2 | G6: =1+($T$4/12) | H6: =(H5+F6)*G6 | I6: 86 | J6: =$T$2 | K6: =1+($T$4/12) | L6: =(L5+J6)*K6 | M6: 127 | N6: =$T$2 | O6: =1+($T$4/12) | P6: =(P5+N6)*O6 | Q6: 4 | R6: =R5+$T$3
A7: 5 | B7: =$T$2 | C7: =1+($T$4/12) | D7: =(D6+B7)*C7 | E7: 46 | F7: =$T$2 | G7: =1+($T$4/12) | H7: =(H6+F7)*G7 | I7: 87 | J7: =$T$2 | K7: =1+($T$4/12) | L7: =(L6+J7)*K7 | M7: 128 | N7: =$T$2 | O7: =1+($T$4/12) | P7: =(P6+N7)*O7 | Q7: 5 | R7: =R6+$T$3 | T7: =VLOOKUP(T5,Q3:R82,2) | U7: Benefits Received
A8: 6 | B8: =$T$2 | C8: =1+($T$4/12) | D8: =(D7+B8)*C8 | E8: 47 | F8: =$T$2 | G8: =1+($T$4/12) | H8: =(H7+F8)*G8 | I8: 88 | J8: =$T$2 | K8: =1+($T$4/12) | L8: =(L7+J8)*K8 | M8: 129 | N8: =$T$2 | O8: =1+($T$4/12) | P8: =(P7+N8)*O8 | Q8: 6 | R8: =R7+$T$3
A9: 7 | B9: =$T$2 | C9: =1+($T$4/12) | D9: =(D8+B9)*C9 | E9: 48 | F9: =$T$2 | G9: =1+($T$4/12) | H9: =(H8+F9)*G9 | I9: 89 | J9: =$T$2 | K9: =1+($T$4/12) | L9: =(L8+J9)*K9 | M9: 130 | N9: =$T$2 | O9: =1+($T$4/12) | P9: =(P8+N9)*O9 | Q9: 7 | R9: =R8+$T$3 | T9: =NPER(T4/12,T2,0,-T7) | U9: What Month would you breakeven?
A10: 8 | B10: =$T$2 | C10: =1+($T$4/12) | D10: =(D9+B10)*C10 | E10: 49 | F10: =$T$2 | G10: =1+($T$4/12) | H10: =(H9+F10)*G10 | I10: 90 | J10: =$T$2 | K10: =1+($T$4/12) | L10: =(L9+J10)*K10 | M10: 131 | N10: =$T$2 | O10: =1+($T$4/12) | P10: =(P9+N10)*O10 | Q10: 8 | R10: =R9+$T$3 | T10: =T9/12 | U10: Number of years you need to self insure
A11: 9 | B11: =$T$2 | C11: =1+($T$4/12) | D11: =(D10+B11)*C11 | E11: 50 | F11: =$T$2 | G11: =1+($T$4/12) | H11: =(H10+F11)*G11 | I11: 91 | J11: =$T$2 | K11: =1+($T$4/12) | L11: =(L10+J11)*K11 | M11: 132 | N11: =$T$2 | O11: =1+($T$4/12) | P11: =(P10+N11)*O11 | Q11: 9 | R11: =R10+$T$3
A12: 10 | B12: =$T$2 | C12: =1+($T$4/12) | D12: =(D11+B12)*C12 | E12: 51 | F12: =$T$2 | G12: =1+($T$4/12) | H12: =(H11+F12)*G12 | I12: 92 | J12: =$T$2 | K12: =1+($T$4/12) | L12: =(L11+J12)*K12 | M12: 133 | N12: =$T$2 | O12: =1+($T$4/12) | P12: =(P11+N12)*O12 | Q12: 10 | R12: =R11+$T$3
A13: 11 | B13: =$T$2 | C13: =1+($T$4/12) | D13: =(D12+B13)*C13 | E13: 52 | F13: =$T$2 | G13: =1+($T$4/12) | H13: =(H12+F13)*G13 | I13: 93 | J13: =$T$2 | K13: =1+($T$4/12) | L13: =(L12+J13)*K13 | M13: 134 | N13: =$T$2 | O13: =1+($T$4/12) | P13: =(P12+N13)*O13 | Q13: 11 | R13: =R12+$T$3
A14: 12 | B14: =$T$2 | C14: =1+($T$4/12) | D14: =(D13+B14)*C14 | E14: 53 | F14: =$T$2 | G14: =1+($T$4/12) | H14: =(H13+F14)*G14 | I14: 94 | J14: =$T$2 | K14: =1+($T$4/12) | L14: =(L13+J14)*K14 | M14: 135 | N14: =$T$2 | O14: =1+($T$4/12) | P14: =(P13+N14)*O14 | Q14: 12 | R14: =R13+$T$3
A15: 13 | B15: =$T$2 | C15: =1+($T$4/12) | D15: =(D14+B15)*C15 | E15: 54 | F15: =$T$2 | G15: =1+($T$4/12) | H15: =(H14+F15)*G15 | I15: 95 | J15: =$T$2 | K15: =1+($T$4/12) | L15: =(L14+J15)*K15 | M15: 136 | N15: =$T$2 | O15: =1+($T$4/12) | P15: =(P14+N15)*O15 | Q15: 13 | R15: =R14+$T$3
A16: 14 | B16: =$T$2 | C16: =1+($T$4/12) | D16: =(D15+B16)*C16 | E16: 55 | F16: =$T$2 | G16: =1+($T$4/12) | H16: =(H15+F16)*G16 | I16: 96 | J16: =$T$2 | K16: =1+($T$4/12) | L16: =(L15+J16)*K16 | M16: 137 | N16: =$T$2 | O16: =1+($T$4/12) | P16: =(P15+N16)*O16 | Q16: 14 | R16: =R15+$T$3
A17: 15 | B17: =$T$2 | C17: =1+($T$4/12) | D17: =(D16+B17)*C17 | E17: 56 | F17: =$T$2 | G17: =1+($T$4/12) | H17: =(H16+F17)*G17 | I17: 97 | J17: =$T$2 | K17: =1+($T$4/12) | L17: =(L16+J17)*K17 | M17: 138 | N17: =$T$2 | O17: =1+($T$4/12) | P17: =(P16+N17)*O17 | Q17: 15 | R17: =R16+$T$3
A18: 16 | B18: =$T$2 | C18: =1+($T$4/12) | D18: =(D17+B18)*C18 | E18: 57 | F18: =$T$2 | G18: =1+($T$4/12) | H18: =(H17+F18)*G18 | I18: 98 | J18: =$T$2 | K18: =1+($T$4/12) | L18: =(L17+J18)*K18 | M18: 139 | N18: =$T$2 | O18: =1+($T$4/12) | P18: =(P17+N18)*O18 | Q18: 16 | R18: =R17+$T$3
A19: 17 | B19: =$T$2 | C19: =1+($T$4/12) | D19: =(D18+B19)*C19 | E19: 58 | F19: =$T$2 | G19: =1+($T$4/12) | H19: =(H18+F19)*G19 | I19: 99 | J19: =$T$2 | K19: =1+($T$4/12) | L19: =(L18+J19)*K19 | M19: 140 | N19: =$T$2 | O19: =1+($T$4/12) | P19: =(P18+N19)*O19 | Q19: 17 | R19: =R18+$T$3
A20: 18 | B20: =$T$2 | C20: =1+($T$4/12) | D20: =(D19+B20)*C20 | E20: 59 | F20: =$T$2 | G20: =1+($T$4/12) | H20: =(H19+F20)*G20 | I20: 100 | J20: =$T$2 | K20: =1+($T$4/12) | L20: =(L19+J20)*K20 | M20: 141 | N20: =$T$2 | O20: =1+($T$4/12) | P20: =(P19+N20)*O20 | Q20: 18 | R20: =R19+$T$3
A21: 19 | B21: =$T$2 | C21: =1+($T$4/12) | D21: =(D20+B21)*C21 | E21: 60 | F21: =$T$2 | G21: =1+($T$4/12) | H21: =(H20+F21)*G21 | I21: 101 | J21: =$T$2 | K21: =1+($T$4/12) | L21: =(L20+J21)*K21 | M21: 142 | N21: =$T$2 | O21: =1+($T$4/12) | P21: =(P20+N21)*O21 | Q21: 19 | R21: =R20+$T$3
A22: 20 | B22: =$T$2 | C22: =1+($T$4/12) | D22: =(D21+B22)*C22 | E22: 61 | F22: =$T$2 | G22: =1+($T$4/12) | H22: =(H21+F22)*G22 | I22: 102 | J22: =$T$2 | K22: =1+($T$4/12) | L22: =(L21+J22)*K22 | M22: 143 | N22: =$T$2 | O22: =1+($T$4/12) | P22: =(P21+N22)*O22 | Q22: 20 | R22: =R21+$T$3
... A43: 41 | B43: =$T$2 | C43: =1+($T$4/12) | D43: =(D42+B43)*C43 | E43: 82 | F43: =$T$2 | G43: =1+($T$4/12) | H43: =(H42+F43)*G43 | I43: 123 | J43: =$T$2 | K43: =1+($T$4/12) | L43: =(L42+J43)*K43 | M43: 164 | N43: =$T$2 | O43: =1+($T$4/12) | P43: =(P42+N43)*O43 | Q43: 41 | R43: =R42+$T$3
A44: Month | B44: Mo/$ | C44: Mo/Ret | D44: Investment | E44: Month | F44: Mo/$ | G44: Mo/Ret | H44: Investment | I44: Month | J44: Mo/$ | K44: Mo/Ret | L44: Investment | M44: Month | N44: Mo/$ | O44: Mo/Ret | P44: Investment | R44: Benefit
A45: 165 | B45: =$T$2 | C45: =1+($T$4/12) | D45: =(P43+B45)*C45 | E45: 203 | F45: =$T$2 | G45: =1+($T$4/12) | H45: =(D82+F45)*G45 | I45: 241 | J45: =$T$2 | K45: =1+($T$4/12) | L45: =(H82+J45)*K45 | M45: 279 | N45: =$T$2 | O45: =1+($T$4/12) | P45: =(L82+N45)*O45 | Q45: 42 | R45: =R43+$T$3
A46: 166 | B46: =$T$2 | C46: =1+($T$4/12) | D46: =(D45+B46)*C46 | E46: 204 | F46: =$T$2 | G46: =1+(0.06/12) | H46: =(H45+F46)*G46 | I46: 242 | J46: =$T$2 | K46: =1+($T$4/12) | L46: =(L45+J46)*K46 | M46: 280 | N46: =$T$2 | O46: =1+($T$4/12) | P46: =(P45+N46)*O46 | Q46: 43 | R46: =R45+$T$3
A47: 167 | B47: =$T$2 | C47: =1+($T$4/12) | D47: =(D46+B47)*C47 | E47: 205 | F47: =$T$2 | G47: =1+(0.06/12) | H47: =(H46+F47)*G47 | I47: 243 | J47: =$T$2 | K47: =1+($T$4/12) | L47: =(L46+J47)*K47 | M47: 281 | N47: =$T$2 | O47: =1+($T$4/12) | P47: =(P46+N47)*O47 | Q47: 44 | R47: =R46+$T$3
A48: 168 | B48: =$T$2 | C48: =1+($T$4/12) | D48: =(D47+B48)*C48 | E48: 206 | F48: =$T$2 | G48: =1+(0.06/12) | H48: =(H47+F48)*G48 | I48: 244 | J48: =$T$2 | K48: =1+($T$4/12) | L48: =(L47+J48)*K48 | M48: 282 | N48: =$T$2 | O48: =1+($T$4/12) | P48: =(P47+N48)*O48 | Q48: 45 | R48: =R47+$T$3
A49: 169 | B49: =$T$2 | C49: =1+($T$4/12) | D49: =(D48+B49)*C49 | E49: 207 | F49: =$T$2 | G49: =1+(0.06/12) | H49: =(H48+F49)*G49 | I49: 245 | J49: =$T$2 | K49: =1+($T$4/12) | L49: =(L48+J49)*K49 | M49: 283 | N49: =$T$2 | O49: =1+($T$4/12) | P49: =(P48+N49)*O49 | Q49: 46 | R49: =R48+$T$3
A50: 170 | B50: =$T$2 | C50: =1+($T$4/12) | D50: =(D49+B50)*C50 | E50: 208 | F50: =$T$2 | G50: =1+(0.06/12) | H50: =(H49+F50)*G50 | I50: 246 | J50: =$T$2 | K50: =1+($T$4/12) | L50: =(L49+J50)*K50 | M50: 284 | N50: =$T$2 | O50: =1+($T$4/12) | P50: =(P49+N50)*O50 | Q50: 47 | R50: =R49+$T$3
A51: 171 | B51: =$T$2 | C51: =1+($T$4/12) | D51: =(D50+B51)*C51 | E51: 209 | F51: =$T$2 | G51: =1+(0.06/12) | H51: =(H50+F51)*G51 | I51: 247 | J51: =$T$2 | K51: =1+($T$4/12) | L51: =(L50+J51)*K51 | M51: 285 | N51: =$T$2 | O51: =1+($T$4/12) | P51: =(P50+N51)*O51 | Q51: 48 | R51: =R50+$T$3
A52: 172 | B52: =$T$2 | C52: =1+($T$4/12) | D52: =(D51+B52)*C52 | E52: 210 | F52: =$T$2 | G52: =1+(0.06/12) | H52: =(H51+F52)*G52 | I52: 248 | J52: =$T$2 | K52: =1+($T$4/12) | L52: =(L51+J52)*K52 | M52: 286 | N52: =$T$2 | O52: =1+($T$4/12) | P52: =(P51+N52)*O52 | Q52: 49 | R52: =R51+$T$3
A53: 173 | B53: =$T$2 | C53: =1+($T$4/12) | D53: =(D52+B53)*C53 | E53: 211 | F53: =$T$2 | G53: =1+(0.06/12) | H53: =(H52+F53)*G53 | I53: 249 | J53: =$T$2 | K53: =1+($T$4/12) | L53: =(L52+J53)*K53 | M53: 287 | N53: =$T$2 | O53: =1+($T$4/12) | P53: =(P52+N53)*O53 | Q53: 50 | R53: =R52+$T$3
A54: 174 | B54: =$T$2 | C54: =1+($T$4/12) | D54: =(D53+B54)*C54 | E54: 212 | F54: =$T$2 | G54: =1+(0.06/12) | H54: =(H53+F54)*G54 | I54: 250 | J54: =$T$2 | K54: =1+($T$4/12) | L54: =(L53+J54)*K54 | M54: 288 | N54: =$T$2 | O54: =1+($T$4/12) | P54: =(P53+N54)*O54 | Q54: 51 | R54: =R53+$T$3
A55: 175 | B55: =$T$2 | C55: =1+($T$4/12) | D55: =(D54+B55)*C55 | E55: 213 | F55: =$T$2 | G55: =1+(0.06/12) | H55: =(H54+F55)*G55 | I55: 251 | J55: =$T$2 | K55: =1+($T$4/12) | L55: =(L54+J55)*K55 | M55: 289 | N55: =$T$2 | O55: =1+($T$4/12) | P55: =(P54+N55)*O55 | Q55: 52 | R55: =R54+$T$3
A56: 176 | B56: =$T$2 | C56: =1+($T$4/12) | D56: =(D55+B56)*C56 | E56: 214 | F56: =$T$2 | G56: =1+(0.06/12) | H56: =(H55+F56)*G56 | I56: 252 | J56: =$T$2 | K56: =1+($T$4/12) | L56: =(L55+J56)*K56 | M56: 290 | N56: =$T$2 | O56: =1+($T$4/12) | P56: =(P55+N56)*O56 | Q56: 53 | R56: =R55+$T$3
A57: 177 | B57: =$T$2 | C57: =1+($T$4/12) | D57: =(D56+B57)*C57 | E57: 215 | F57: =$T$2 | G57: =1+(0.06/12) | H57: =(H56+F57)*G57 | I57: 253 | J57: =$T$2 | K57: =1+($T$4/12) | L57: =(L56+J57)*K57 | M57: 291 | N57: =$T$2 | O57: =1+($T$4/12) | P57: =(P56+N57)*O57 | Q57: 54 | R57: =R56+$T$3
... A82: 202 | B82: =$T$2 | C82: =1+($T$4/12) | D82: =(D81+B82)*C82 | E82: 240 | F82: =$T$2 | G82: =1+(0.06/12) | H82: =(H81+F82)*G82 | I82: 278 | J82: =$T$2 | K82: =1+($T$4/12) | L82: =(L81+J82)*K82 | M82: 316 | N82: =$T$2 | O82: =1+($T$4/12) | P82: =(P81+N82)*O82 | Q82: 79 | R82: =R81+$T$3
